odoo/addons/server_environment_files_sample/README.rst
odoo/addons/server_environment_files_sample/__init__.py
odoo/addons/server_environment_files_sample/__manifest__.py
odoo/addons/server_environment_files_sample/default/base.conf
odoo/addons/server_environment_files_sample/default/mytopic.conf
odoo/addons/server_environment_files_sample/i18n/server_environment_files.pot
odoo/addons/server_environment_files_sample/i18n/server_environment_files_sample.pot
odoo/addons/server_environment_files_sample/preprod/mytopic.conf
odoo/addons/server_environment_files_sample/prod/base.conf
odoo/addons/server_environment_files_sample/prod/mytopic.conf
odoo/addons/server_environment_files_sample/readme/CONTRIBUTORS.rst
odoo/addons/server_environment_files_sample/readme/DESCRIPTION.rst
odoo/addons/server_environment_files_sample/readme/INSTALL.rst
odoo/addons/server_environment_files_sample/static/description/icon.png
odoo/addons/server_environment_files_sample/static/description/index.html
odoo/addons/server_environment_files_sample/test/base.conf
odoo/addons/server_environment_files_sample/test/mytopic.conf
odoo/addons/server_environment_files_sample/test/pos_environment.conf
odoo_addon_server_environment_files_sample-15.0.1.0.0.4.dist-info/METADATA
odoo_addon_server_environment_files_sample-15.0.1.0.0.4.dist-info/WHEEL
odoo_addon_server_environment_files_sample-15.0.1.0.0.4.dist-info/top_level.txt
odoo_addon_server_environment_files_sample-15.0.1.0.0.4.dist-info/RECORD
