Metadata-Version: 2.1
Name: odoo-addon-server-environment-files-sample
Version: 15.0.1.0.0.4
Summary: sample config file for server_environment
Home-page: https://github.com/OCA/server-env
Author: Camptocamp,Odoo Community Association (OCA)
Author-email: support@odoo-community.org
License: GPL-3 or any later version
Platform: UNKNOWN
Classifier: Programming Language :: Python
Classifier: Framework :: Odoo
Classifier: Framework :: Odoo :: 15.0
Classifier: License :: OSI Approved :: GNU General Public License v3 or later (GPLv3+)
Requires-Python: >=3.8
Requires-Dist: odoo <15.1dev,>=15.0a
